setup.py
pycclib/__init__.py
pycclib/cclib.py
pycclib/version.py
pycclib.egg-info/PKG-INFO
pycclib.egg-info/SOURCES.txt
pycclib.egg-info/dependency_links.txt
pycclib.egg-info/requires.txt
pycclib.egg-info/top_level.txt
tests/__init__.py
tests/test_auth.py
tests/test_cclib.py
tests/test_pycclib.py